README.rst
setup.py
src/sphinxcontrib/__init__.py
src/sphinxcontrib/ros/__init__.py
src/sphinxcontrib/ros/api.py
src/sphinxcontrib/ros/base.py
src/sphinxcontrib/ros/message.py
src/sphinxcontrib/ros/package.py
src/sphinxcontrib_ros.egg-info/PKG-INFO
src/sphinxcontrib_ros.egg-info/SOURCES.txt
src/sphinxcontrib_ros.egg-info/dependency_links.txt
src/sphinxcontrib_ros.egg-info/namespace_packages.txt
src/sphinxcontrib_ros.egg-info/requires.txt
src/sphinxcontrib_ros.egg-info/top_level.txt