Metadata-Version: 1.1
Name: sphinxcontrib-ros
Version: 0.0.4
Summary: Sphinx extension forROS(Robot Operating System) documentation
Home-page: https://github.com/otamachan/sphinxcontrib-ros.git
Author: Tamaki Nishino
Author-email: otamachan at gmail.com
License: BSD
Platform: UNKNOWN
Classifier: Development Status :: 3 - Alpha
Classifier: Environment :: Console
Classifier: Environment :: Web Environment
Classifier: Framework :: Sphinx :: Extension
Classifier: License :: OSI Approved :: BSD License
Classifier: Operating System :: OS Independent
Classifier: Programming Language :: Python
Classifier: Topic :: Documentation
Classifier: Topic :: Documentation :: Sphinx
Classifier: Topic :: Utilities
